<?xml version="1.0" encoding="UTF-8"?>
<!DOCTYPE struts PUBLIC
	"-//Apache Software Foundation//DTD Struts Configuration 2.3//EN"
	"http://struts.apache.org/dtds/struts-2.3.dtd">
	<struts>
		<constant name="struts.ui.theme" value="simple"></constant>
		<constant name="struts.i18n.encoding" value="utf-8"></constant>
		<constant name="struts.devMode" value="false"></constant>
		
		<include file="struts-user.xml" /><!-- 引用前台的struts配置文件 -->
		<include file="struts-admin.xml" /> <!-- 引用后台的struts配置文件 -->
	</struts>